<lcgdict>

  <class name="PortableHostCollection<TrackLayout<pixelTopology::Phase1>>"/>
  <read
    sourceClass="PortableHostCollection<TrackLayout<pixelTopology::Phase1>>"
    targetClass="PortableHostCollection<TrackLayout<pixelTopology::Phase1>>"
    version="[1-]"
    source="TrackLayout<pixelTopology::Phase1> layout_;"
    target="buffer_"
    embed="false">
  <![CDATA[
    PortableHostCollection<TrackLayout<pixelTopology::Phase1>>::ROOTReadStreamer(newObj, onfile.layout_);
  ]]>
  </read>
  <class name="TrackSoAHost<pixelTopology::Phase1>"/>
  <class name="edm::Wrapper<TrackSoAHost<pixelTopology::Phase1>>" splitLevel="0"/>

  <class name="PortableHostCollection<TrackLayout<pixelTopology::Phase2>>"/>
  <read
    sourceClass="PortableHostCollection<TrackLayout<pixelTopology::Phase2>>"
    targetClass="PortableHostCollection<TrackLayout<pixelTopology::Phase2>>"
    version="[1-]"
    source="TrackLayout<pixelTopology::Phase2> layout_;"
    target="buffer_"
    embed="false">
  <![CDATA[
    PortableHostCollection<TrackLayout<pixelTopology::Phase2>>::ROOTReadStreamer(newObj, onfile.layout_);
  ]]>
  </read>
  <class name="TrackSoAHost<pixelTopology::Phase2>"/>
  <class name="edm::Wrapper<TrackSoAHost<pixelTopology::Phase2>>" splitLevel="0"/>

</lcgdict>
